clattr/__init__.py
clattr/api.py
clattr/inputs.py
clattr/interpret_string.py
clattr/tools.py
clattr-0.0.1.dist-info/LICENSE
clattr-0.0.1.dist-info/WHEEL
clattr-0.0.1.dist-info/METADATA
clattr-0.0.1.dist-info/RECORD
