Metadata-Version: 2.1
Name: clattr
Version: 0.0.1
Summary: Construct a comand line interface based on a function or class
License: MIT
Author: Tom Dimiduk
Author-email: tom@dimiduk.net
Requires-Python: >=3.6
Classifier: License :: OSI Approved :: MIT License
Classifier: Programming Language :: Python :: 3
Classifier: Programming Language :: Python :: 3.6
Classifier: Programming Language :: Python :: 3.7
Classifier: Programming Language :: Python :: 3.8
Classifier: Programming Language :: Python :: 3.9
